[
  {
    "value": "Avon and Somerset Constabulary",
    "key": 1
  },
  {
    "value": "Bedfordshire Police",
    "key": 2
  },
  {
    "value": "British Transport Police",
    "key": 3
  },
  {
    "value": "Cambridgeshire Constabulary",
    "key": 4
  },
  {
    "value": "Cheshire Constabulary",
    "key": 5
  },
  {
    "value": "City of London Police",
    "key": 6
  },
  {
    "value": "Cleveland Police",
    "key": 7
  },
  {
    "value": "Cumbria Constabulary",
    "key": 8
  },
  {
    "value": "Derbyshire Constabulary",
    "key": 9
  },
  {
    "value": "Devon & Cornwall Police",
    "key": 10
  },
  {
    "value": "Dorset Police",
    "key": 11
  },
  {
    "value": "Durham Constabulary",
    "key": 12
  },
  {
    "value": "Dyfed-Powys Police",
    "key": 13
  },
  {
    "value": "Essex Police",
    "key": 14
  },
  {
    "value": "Gloucestershire Constabulary",
    "key": 15
  },
  {
    "value": "Greater Manchester Police",
    "key": 16
  },
  {
    "value": "Gwent Police",
    "key": 17
  },
  {
    "value": "Hampshire Constabulary",
    "key": 18
  },
  {
    "value": "Hertfordshire Constabulary",
    "key": 19
  },
  {
    "value": "Humberside Police",
    "key": 20
  },
  {
    "value": "Kent Police",
    "key": 21
  },
  {
    "value": "Lancashire Constabulary",
    "key": 22
  },
  {
    "value": "Leicestershire Police",
    "key": 23
  },
  {
    "value": "Lincolnshire Police",
    "key": 24
  },
  {
    "value": "Merseyside Police",
    "key": 25
  },
  {
    "value": "Metropolitan Police Service",
    "key": 26
  },
  {
    "value": "Norfolk Constabulary",
    "key": 27
  },
  {
    "value": "North Wales Police",
    "key": 28
  },
  {
    "value": "North Yorkshire Police",
    "key": 29
  },
  {
    "value": "Northamptonshire Police",
    "key": 30
  },
  {
    "value": "Police Service of Northern Ireland",
    "key": 31
  },
  {
    "value": "Northumbria Police",
    "key": 32
  },
  {
    "value": "Nottinghamshire Police",
    "key": 33
  },
  {
    "value": "South Wales Police",
    "key": 34
  },
  {
    "value": "South Yorkshire Police",
    "key": 35
  },
  {
    "value": "Staffordshire Police",
    "key": 36
  },
  {
    "value": "Suffolk Constabulary",
    "key": 37
  },
  {
    "value": "Sussex Police",
    "key": 38
  },
  {
    "value": "Thames Valley Police",
    "key": 39
  },
  {
    "value": "Warwickshire Police",
    "key": 40
  },
  {
    "value": "West Mercia Police",
    "key": 41
  },
  {
    "value": "West Midlands Police",
    "key": 42
  },
  {
    "value": "West Yorkshire Police",
    "key": 43
  },
  {
    "value": "Wiltshire Police",
    "key": 44
  },
  {
    "value": "Surrey Police",
    "key": 45
  }
]
